codedepot_git_ai-0.1.6.dist-info/METADATA
codedepot_git_ai-0.1.6.dist-info/WHEEL
codedepot_git_ai-0.1.6.dist-info/entry_points.txt
codedepot_git_ai-0.1.6.dist-info/licenses/LICENSE
git_ai/__init__.py
git_ai/cmd/__init__.py
git_ai/cmd/ai_repo/__init__.py
git_ai/cmd/ai_repo/ai_repo.py
git_ai/cmd/ai_repo/ai_repo_config.py
git_ai/cmd/ai_repo/ai_repo_log.py
git_ai/cmd/ai_repo/credentials.py
git_ai/cmd/constants.py
git_ai/cmd/diff.py
git_ai/cmd/error.py
git_ai/cmd/init.py
git_ai/cmd/input_repo.py
git_ai/cmd/log.py
git_ai/cmd/merge_exp.py
git_ai/cmd/runner.py
git_ai/errors/__init__.py
git_ai/errors/errors.py
git_ai/main/__init__.py
git_ai/main/main.py
git_ai/metrics/__init__.py
git_ai/metrics/experiment.py
git_ai/metrics/writer.py
git_ai/pygitutils/__init__.py
git_ai/pygitutils/pygitutils.py
git_ai/test/__init__.py
git_ai/test/test_ai_repo.py
git_ai/test/topologies/cnn.1
git_ai/test/topologies/cnn.2
git_ai/test/topologies/cnn.3
git_ai/test/topologies/cnn.4
git_ai/test/utils/__init__.py
git_ai/test/utils/ai_repo_read.py
git_ai/test/utils/data_gen.py
git_ai/test/utils/interuptable_test.py
git_ai/test/utils/setup_repo.py
git_ai/test/utils/testutils.py
git_ai/utils/__init__.py
git_ai/utils/utils.py
codedepot_git_ai-0.1.6.dist-info/RECORD
