Metadata-Version: 2.1
Name: codedepot-git-ai
Version: 0.1.6
Summary: Dataset and model support for git
Author-Email: CodeDepot <contact@codedepot.ai>
License: MIT
Classifier: License :: OSI Approved :: MIT License
Classifier: Operating System :: OS Independent
Classifier: Programming Language :: Python :: 3
Project-URL: Homepage, https://github.com/codedepotai/git-ai
Project-URL: Issues, https://github.com/codedepotai/git-ai/issues
Requires-Python: >=3.10
Requires-Dist: torch
Requires-Dist: paramiko
Requires-Dist: prompt_toolkit
Requires-Dist: pygit2>=1.4.1
Requires-Dist: tensorboard==2.16.2
Requires-Dist: numpy==1.26.4
